mathworld/__init__.py
mathworld/elements.py
mathworld/equations.py
mathworld-0.1.1.dist-info/LICENSE
mathworld-0.1.1.dist-info/METADATA
mathworld-0.1.1.dist-info/WHEEL
mathworld-0.1.1.dist-info/top_level.txt
mathworld-0.1.1.dist-info/RECORD
