Metadata-Version: 2.1
Name: mathworld
Version: 0.1.1
Summary: A python module for using sympy with analytic geometry
Home-page: https://github.com/PinkPantherPC/MathWorld
Author: Tobia Petrolini
License: MIT
Keywords: math,geometry,analytic,line,point,sympy,symbolic,calculation,CAS
Classifier: Development Status :: 2 - Pre-Alpha
Classifier: Intended Audience :: Developers
Classifier: Intended Audience :: Education
Classifier: Topic :: Scientific/Engineering :: Mathematics
Classifier: Programming Language :: Python :: 3
Classifier: License :: OSI Approved :: MIT License
Classifier: Operating System :: OS Independent
Requires-Python: >=3.10
License-File: LICENSE
Requires-Dist: sympy>=1.13.3
